risk_model_tool/__init__.py
risk_model_tool/analysis/__init__.py
risk_model_tool/analysis/calculate_psi.py
risk_model_tool/analysis/contingency.py
risk_model_tool/analysis/data_overview.py
risk_model_tool/analysis/var_stability.py
risk_model_tool/analysis/variable_dictionary.py
risk_model_tool/analysis/woe_tools.py
risk_model_tool/model/__init__.py
risk_model_tool/model/model_building.py
risk_model_tool/model/model_validation.py
risk_model_tool/model/one_var.py
risk_model_tool/model/predict_gbdtlr.py
risk_model_tool/model/train_lightgbm.py
risk_model_tool/model/train_nn.py
risk_model_tool/preprocess/__init__.py
risk_model_tool/preprocess/preprocess.py
risk_model_tool/preprocess/sparse_one_hot.py
risk_model_tool/utils/__init__.py
risk_model_tool/utils/autoexcel.py
risk_model_tool/utils/df_to_highchart.py
risk_model_tool/utils/mail_sender.py
risk_model_tool/utils/plot_chs_config.py
risk_model_tool-0.1.3.dist-info/LICENSE
risk_model_tool-0.1.3.dist-info/WHEEL
risk_model_tool-0.1.3.dist-info/METADATA
risk_model_tool-0.1.3.dist-info/RECORD
