Metadata-Version: 2.1
Name: risk-model-tool
Version: 0.1.3
Summary: This is a package help analyzing, preprocessing, and modeling in credit default projects.
License: MIT
Author: Wenjia Zhu, Jianhong Jiang, Jingcheng Qiu
Requires-Python: >=3.9,<4.0
Classifier: License :: OSI Approved :: MIT License
Classifier: Programming Language :: Python :: 3
Classifier: Programming Language :: Python :: 3.10
Classifier: Programming Language :: Python :: 3.9
Requires-Dist: Pillow (>=9.0.1,<10.0.0)
Requires-Dist: matplotlib (>=3.5.1,<4.0.0)
Requires-Dist: numpy (>=1.22.2,<2.0.0)
Requires-Dist: openpyxl (>=3.0.9,<4.0.0)
Requires-Dist: pandas (>=1.4.1,<2.0.0)
Requires-Dist: python-highcharts (>=0.4.2,<0.5.0)
Requires-Dist: scikit-learn (>=1.0.2,<2.0.0)
